prenotazione_unimi/__main__.py
prenotazione_unimi/easystaff.py
prenotazione_unimi/exceptions.py
prenotazione_unimi-2.0.3.dist-info/LICENSE
prenotazione_unimi-2.0.3.dist-info/METADATA
prenotazione_unimi-2.0.3.dist-info/WHEEL
prenotazione_unimi-2.0.3.dist-info/top_level.txt
prenotazione_unimi-2.0.3.dist-info/RECORD
